[
  {
    "id": 4740248,
    "name": "Meamer",
    "source_url": "https://www.chabad.org/library/article_cdo/aid/4740248/jewish/Meamer-Gathering.htm",
    "fetch_status": "ok",
    "definition": null,
    "activities_to_avoid": null,
    "body_lines": [
      "Binding or gathering produce, the",
      "av",
      "melachah",
      "of",
      "me’amer",
      ", is forbidden on",
      "Shabbat",
      ".",
      "1",
      "In the",
      "Mishkan",
      ",",
      "me’amer",
      "involved",
      "gathering produce in the field after it was cut. Since the acts which are",
      "forbidden on",
      "Shabbat",
      "are derived from the way the",
      "melachot",
      "were done in the",
      "Mishkan",
      ", there are a number of",
      "restrictions to this",
      "melachah",
      ".",
      "Gidulei Karka -",
      "The",
      "produce must have grown from the ground.",
      "One only",
      "transgresses the biblical prohibition of"
    ]
  },
  {
    "id": 4739406,
    "name": "Choresh",
    "source_url": "https://www.chabad.org/library/article_cdo/aid/4739406/jewish/Choresh-Plowing.htm",
    "fetch_status": "error: HTTP Error 403: Forbidden"
  },
  {
    "id": 4786919,
    "name": "Dosh",
    "source_url": "https://www.chabad.org/library/article_cdo/aid/4786919/jewish/Dosh-Threshing.htm",
    "fetch_status": "ok",
    "definition": "refers to threshing using a utensil designed for that purpose, or treading on the produce.",
    "activities_to_avoid": null,
    "body_lines": [
      "Threshing, the",
      "av",
      "melachah",
      "of",
      "dosh,",
      "is forbidden on",
      "Shabbat",
      ". In the",
      "Mishkan",
      ",",
      "dosh",
      "was performed by treading or using a flail to beat produce in order to remove the seeds. As such, the",
      "av melachah",
      "of",
      "dosh",
      "refers to threshing using a utensil designed for that purpose, or treading on the produce.",
      "1",
      "Essentially,",
      "dosh",
      "is the removal of foods or liquids from where they are encased.",
      "2",
      "Although this would seem to include most fruits and vegetables that we peel, like bananas and oranges, that is not the case. The threshing in the",
      "Mishkan",
      "was done while the produce was still in the field. Most of our fruits and vegetables are peeled just before they are eaten, and would in fact be rotten if peeled so far in advance. Since the manner is incomparable, it is not included in the",
      "melachah",
      ". Moreover, the peels are directly attached and can be considered part of the fruit itself. Therefore, the removal of their peels is no different than cutting the fruit, which is obviously permitted.",
      "3",
      "One should be careful not to use a peeler on",
      "Shabbat",
      ", however, and use a knife instead."
    ]
  },
  {
    "id": 4788763,
    "name": "Zoreh",
    "source_url": "https://www.chabad.org/library/article_cdo/aid/4788763/jewish/Zoreh-Winnowing.htm",
    "fetch_status": "ok",
    "definition": "refers to the act of removing chaff from grain, using a tool to throw produce into the air, whereby the wind blows the lighter chaff away from the heavier",
    "activities_to_avoid": null,
    "body_lines": [
      "Winnowing,",
      "the",
      "av",
      "melachah",
      "of Zoreh, is forbidden",
      "on",
      "Shabbat",
      ".",
      "1",
      "Winnowing",
      "refers to the act of removing chaff from grain, using a tool to throw produce",
      "into the air, whereby the wind blows the lighter chaff away from the heavier",
      "kernels.",
      "Halachic",
      "authorities disagree about what exactly is included in this",
      "melachah",
      ". Some assert that Zoreh refers",
      "to the separation of foods and non-foods, specifically using the wind, as it",
      "was done in the",
      "Mishkan",
      ".",
      "2",
      "Others",
      "maintain that wind is not required, and Zoreh refers to the separation of food",
      "from non-food, specifically at the stage when the kernels are still together",
      "with their chaff. All later refinements of the food are not included in Zoreh,",
      "regardless of the method.",
      "3",
      "The",
      "Jerusalem Talmud"
    ]
  },
  {
    "id": 4740282,
    "name": "Tochen",
    "source_url": "https://www.chabad.org/library/article_cdo/aid/4740282/jewish/Tochen-Grinding.htm",
    "fetch_status": "error: HTTP Error 403: Forbidden"
  },
  {
    "id": 4817714,
    "name": "Meraked",
    "source_url": "https://www.chabad.org/library/article_cdo/aid/4817714/jewish/Meraked-Sifting.htm",
    "fetch_status": "error: HTTP Error 403: Forbidden"
  },
  {
    "id": 4819033,
    "name": "Losh",
    "source_url": "https://www.chabad.org/library/article_cdo/aid/4819033/jewish/Losh-Kneading.htm",
    "fetch_status": "ok",
    "definition": "Kneading invariably involves two steps: a) Pouring the liquid into the flour; b) Mixing the flour and water together to make a dough. There is a Talmudic dispute regarding what exactly defines",
    "activities_to_avoid": null,
    "body_lines": [
      "Kneading, the",
      "av",
      "melachah",
      "of",
      "losh,",
      "is forbidden on",
      "Shabbat",
      ". The",
      "melachah",
      "encompasses all activities which, like kneading, join small particles into one mass using liquid, and applies to both foods and non-foods. It also includes later treatment of dough, like basting or braiding.",
      "1",
      "Kneading invariably involves two steps: a) Pouring the liquid into the flour; b) Mixing the flour and water together to make a dough. There is a Talmudic dispute regarding what exactly defines",
      "losh",
      ".",
      "2",
      "Rebbi says that just pouring the liquid over the flour is already",
      "losh,",
      "since the flour and water fuse on impact. Kneading them together is also Biblically forbidden, but as an independent, additional transgression. Rabbi Yosi Bar",
      "Yehuda",
      ", however, says that one only transgresses",
      "losh",
      "by mixing the ingredients together and not by merely pouring the liquid over the flour. While some halachic authorities, most notably Sefer Hateruma, follow Rebbi’s interpretation, the vast majority side with Rabbi Yosi.",
      "3",
      "There are a variety of substances that can be kneaded with liquid. Some, like fine flour, completely mix with water to the extent that the flour becomes a different entity—dough. These substances are halachically termed “",
      "bar gibul",
      ".” There are other substances which are not kneadable, like oats or finely diced vegetables. When these are mixed with water they just clump together but don't transform into a new entity. These are called “",
      "lav bar gibul",
      ".” It is apparent that Rabbi Yosi’s ruling applies to",
      "bar gibul",
      "substances. The authorities debate, however, what he would say about kneading"
    ]
  },
  {
    "id": 4844108,
    "name": "Gozez",
    "source_url": "https://www.chabad.org/library/article_cdo/aid/4844108/jewish/Gozez-Shearing.htm",
    "fetch_status": "ok",
    "definition": ", and involves cutting or uprooting hair, nails, or anything else that grows from a person, animal, or bird.",
    "activities_to_avoid": null,
    "body_lines": [
      "Shearing, the",
      "av",
      "melachah",
      "of",
      "gozez",
      ", is forbidden on",
      "Shabbat",
      ", and involves cutting or uprooting hair, nails, or anything else that grows from a person, animal, or bird.",
      "The Biblical prohibition of",
      "gozez",
      "is only transgressed if one uses an instrument meant for that purpose, like a pair of scissors or a nail clipper.",
      "1",
      "Pulling out hair with one’s hand is not the way hair is typically removed and therefore not prohibited by",
      "gozez.",
      "Likewise, biting one’s nails is not included, since it is not the typical way to cut one’s nails. Nevertheless, the Sages prohibited these activities because they closely resemble the Biblical prohibition.",
      "2",
      "In a scenario where pulling out hair with one’s hand is normal, however, like tweezing (which is considered using one’s hand), doing so is considered Biblically forbidden.",
      "3",
      "Gozez",
      "is prohibited even after the skin has been removed from an animal.",
      "4",
      "As such, one should not pull out fur from a fur coat.",
      "5",
      "Cutting away dead skin, warts, or pimples is also forbidden under",
      "gozez",
      ".",
      "6",
      "Gozez in the Mishkan",
      "Wool was needed to make certain cloth coverings for the",
      "Mishkan"
    ]
  },
  {
    "id": 4853580,
    "name": "Melaben",
    "source_url": "https://www.chabad.org/library/article_cdo/aid/4853580/jewish/Melaben-Bleaching-Laundering.htm",
    "fetch_status": "ok",
    "definition": null,
    "activities_to_avoid": null,
    "body_lines": [
      "Bleaching, the",
      "av",
      "melachah",
      "of",
      "melaben",
      ", is forbidden on",
      "Shabbat",
      ".",
      "1",
      "Some authorities maintain that the",
      "av melachah",
      "is laundering, not bleaching,",
      "2",
      "but the dispute is merely academic, because all agree that any activity which cleans or refines fabric is included in",
      "melaben.",
      "The question is merely which activity is the",
      "av",
      "and which is the",
      "toladah.",
      "According to the",
      "Talmud",
      ", “With regard to clothing (or any absorbent material) soaking is considered laundering.”",
      "3",
      "This indicates that a)",
      "melaben",
      "is transgressed simply by soaking unclean cloth in water, even without scrubbing or removing a stain, and b) soaking is only problematic with absorbent materials like clothes, but does not apply to non-absorbent materials like rubber or leather.",
      "Practically, this means that if a garment has dirt or a stain on it, one may not put any liquid at all",
      "4",
      "on the stain in order to treat it.",
      "5"
    ]
  },
  {
    "id": 4861029,
    "name": "Menapetz",
    "source_url": "https://www.chabad.org/library/article_cdo/aid/4861029/jewish/Menapetz-Combing.htm",
    "fetch_status": "ok",
    "definition": "it involves separating the tangled material by hand. The Meiri, however, writes that only combing using a tool transgresses the",
    "activities_to_avoid": null,
    "body_lines": [
      "Combing clumps of tangled, unprocessed",
      "material is the",
      "av",
      "melachah",
      "of",
      "menapetz",
      "and is forbidden on",
      "Shabbat",
      ".",
      "Even after wool is sheared from the animal and",
      "bleached, it is not yet ready to be made into thread because the hair is still",
      "tangled together.",
      "Menapetz",
      "involves",
      "untangling the strands of material from each other to make them straight and",
      "even.",
      "There are various opinions as to which method",
      "of combing the",
      "melachah",
      "refers to.",
      "According to",
      "Rashi",
      ",",
      "1",
      "it involves separating the tangled material by hand. The Meiri, however, writes",
      "that only combing using a tool transgresses the",
      "av melachah",
      ".",
      "Maimonides",
      "and Rabbi"
    ]
  },
  {
    "id": 4904572,
    "name": "Tzoveya",
    "source_url": "https://www.chabad.org/library/article_cdo/aid/4904572/jewish/Tzoveya-Dyeing.htm",
    "fetch_status": "error: HTTP Error 403: Forbidden"
  },
  {
    "id": 4917849,
    "name": "Toveh",
    "source_url": "https://www.chabad.org/library/article_cdo/aid/4917849/jewish/Toveh-Spinning.htm",
    "fetch_status": "ok",
    "definition": "refers to the act of attaching the ends of the thread to the shafts to",
    "activities_to_avoid": null,
    "body_lines": [
      "Toveh - Spinning",
      "After wool has been properly cleaned and dyed",
      "it is ready to be spun into strands to be used for weaving. Traditionally, this",
      "was done using a spindle. The",
      "melachah",
      "of",
      "toveh",
      "refers to spinning strands into",
      "thread.",
      "1",
      "Twisting",
      "several strands together to form cord or thread (known as",
      "shezirah",
      ") is also prohibited.",
      "2",
      "What does",
      "this mean practically in today’s day and age? If a string of",
      "tzitzit",
      "comes apart, one may not retwist",
      "it on",
      "Shabbat",
      ", for example.",
      "Introduction to the Following",
      "Four Melachot",
      "In the",
      "Mishkan",
      ", weaving was done with a loom. This loom was operated by running lines",
      "of thread through loops of string (heddles) which were attached to a frame that",
      "could be raised and lowered. The threads were stretched so as not to hang",
      "limply, and then attached firmly to a shaft on either side.These threads are"
    ]
  },
  {
    "id": 4937160,
    "name": "Koshair",
    "source_url": "https://www.chabad.org/library/article_cdo/aid/4937160/jewish/Koshair-Tying.htm",
    "fetch_status": "ok",
    "definition": null,
    "activities_to_avoid": null,
    "body_lines": [
      "The",
      "melachah",
      "of",
      "koshair",
      "is the act of binding",
      "by tying a knot. Although most knots are prohibited under this",
      "melachah",
      ", either Biblically or",
      "rabbinically, some are permitted.",
      "Koshair in the Mishkan",
      "A unique blue dye was used for the coverings (",
      "yeriot",
      ") of the",
      "Mishkan",
      ". This dye was",
      "made from a sea creature called the",
      "chilazon",
      ".",
      "To trap the",
      "chilazon",
      ", fishermen",
      "fashioned nets from ropes which were knotted together.",
      "1",
      "Halachic literature describes two types of",
      "knots with regard to the",
      "melachah",
      "of",
      "koshair",
      ":",
      "a)"
    ]
  },
  {
    "id": 4952180,
    "name": "Tofair",
    "source_url": "https://www.chabad.org/library/article_cdo/aid/4952180/jewish/Tofair-Sewing.htm",
    "fetch_status": "ok",
    "definition": null,
    "activities_to_avoid": null,
    "body_lines": [
      "Sewing, the",
      "av",
      "melachah",
      "of",
      "tofair",
      "is",
      "forbidden on",
      "Shabbat",
      ". The purpose of sewing is to attach two pieces of clothing",
      "by stitching them together with thread. Similarly, the",
      "melachah",
      "of",
      "tofair",
      "refers",
      "to attaching two different items using any medium which firmly holds them",
      "together, like gluing, stapling,",
      "1",
      "or pinning.",
      "2",
      "Most",
      "authorities say that",
      "tofair",
      "is",
      "permitted if the person does not intend to keep the items attached for longer",
      "than 24 hours.",
      "3",
      "Tofair",
      "in the Mishkan",
      "Tapestries of woven fabric were used to cover",
      "the"
    ]
  },
  {
    "id": 5009500,
    "name": "Tzad",
    "source_url": "https://www.chabad.org/library/article_cdo/aid/5009500/jewish/Tzod-Trapping.htm",
    "fetch_status": "ok",
    "definition": null,
    "activities_to_avoid": null,
    "body_lines": [
      "Trapping, the",
      "av",
      "melachah",
      "of",
      "tzod,",
      "1",
      "is",
      "forbidden on",
      "Shabbat",
      ". While trapping most creatures is definitely rabbinically",
      "forbidden, the Biblical prohibition of",
      "tzod",
      "is only transgressed if certain conditions are met:",
      "The trapper must intend to benefit from the",
      "animal. The general rule with Biblical prohibitions on",
      "Shabbat",
      "is that they are",
      "only transgressed if one intends to benefit from the forbidden action itself,",
      "not just to offset something else. So one who traps an insect because it was",
      "annoying, for example, only transgresses a rabbinic prohibition.",
      "The creature must be of a species that is",
      "usually trapped by people because it has some sort of use. This would exclude",
      "most insects or rodents.",
      "2",
      "Even if a",
      "person traps one of these insects for some purpose, he is still not liable.",
      "3",
      "The animal must be trapped in a small",
      "enough space that it would be easy for one to grab it from there.",
      "4"
    ]
  },
  {
    "id": 5028250,
    "name": "Shochait",
    "source_url": "https://www.chabad.org/library/article_cdo/aid/5028250/jewish/Shochait-Slaughtering.htm",
    "fetch_status": "error: HTTP Error 403: Forbidden"
  },
  {
    "id": 5099183,
    "name": "Mafshit",
    "source_url": "https://www.chabad.org/library/article_cdo/aid/5099183/jewish/Mafshit-Skinning.htm",
    "fetch_status": "ok",
    "definition": null,
    "activities_to_avoid": null,
    "body_lines": [
      "Skinning the hide off an animal is the",
      "av",
      "melachah",
      "of",
      "mafshit",
      "and is forbidden on",
      "Shabbat",
      ".",
      "1",
      "Rams’ hides and the hides of the",
      "tachash",
      "2",
      "were used as",
      "covers for the",
      "Mishkan",
      ", procured after the animals had been properly",
      "slaughtered.",
      "One may not remove the skin of raw chicken or",
      "fish on",
      "Shabbat",
      ", as this would violate",
      "mafshit",
      ".",
      "The skin of cooked chicken, however, may be removed. This is because cooking",
      "loosens the skin and it is already somewhat removed by the time one comes to",
      "eat it. Also, once the animal has been cooked it is no longer regarded as an",
      "animal but as a food, and the",
      "melachah",
      "of",
      "mafshit"
    ]
  },
  {
    "id": 5163573,
    "name": "Boneh",
    "source_url": "https://www.chabad.org/library/article_cdo/aid/5163573/jewish/Boneh-Building.htm",
    "fetch_status": "ok",
    "definition": "As mentioned, the melacha of Boneh involves assembling and building a permanent structure. The Sages extended the prohibition to include the creation of temporary structures out of concern that it may lead to making a permanent structure.",
    "activities_to_avoid": null,
    "body_lines": [
      "Assembling and building a permanent structure is forbidden on",
      "Shabbat",
      ", and is the",
      "av",
      "melachah",
      "of Boneh.",
      "1",
      "This includes adding to an existing structure as well as leveling the ground to make it more usable.",
      "2",
      "This",
      "melachah",
      "encompasses a wide range of forbidden activities and proper study of the subject will ensure that one observes its laws properly. Here, we will explore some of the basic principles.",
      "Boneh in the Mishkan",
      "The walls of the",
      "Mishkan",
      "were made from specially designed planks of wood that were inserted into sockets on the ground and connected to each other. The construction of these walls and the roof that was stretched over them are the source for the",
      "melachah",
      "of Boneh.",
      "Creating a Land-Based Structure",
      "The",
      "Mishkan",
      ", whose construction serves as the source for all forbidden activity on",
      "Shabbat",
      ", was a land-based structure. Therefore, the",
      "melachah",
      "of Boneh forbids creating any land-based, permanent structures. This includes fences, posts, houses and shelters. Paving a path with tiles",
      "3",
      "or digging a hole in the ground to store things",
      "4",
      "is also considered Boneh, as one is making the space suitable for a constructive purpose."
    ]
  },
  {
    "id": 5580653,
    "name": "Mechabeh",
    "source_url": "https://www.chabad.org/library/article_cdo/aid/5580653/jewish/Mechabeh-Extinguishing.htm",
    "fetch_status": "ok",
    "definition": "appliances is also forbidden on Shabbat, but",
    "activities_to_avoid": null,
    "body_lines": [
      "Extinguishing a flame is forbidden on",
      "Shabbat",
      "and constitutes the",
      "av",
      "melachah",
      "of",
      "mechabeh.",
      "1",
      "Since the 39 general categories of forbidden labor on",
      "Shabbat",
      "are modeled after their sources in the",
      "Mishkan",
      ", it follows that the Biblical prohibition of",
      "mechabeh",
      "is limited to extinguishing a flame to serve a useful purpose, as",
      "mechabeh",
      "was done in the",
      "Mishkan",
      ". For example, some have the custom to light the wicks of the Shabbat candles on Friday afternoon so that they will be easier to light at candle-lighting time. This would be an example of extinguishing for a useful purpose. Practically, there are few examples of this in everyday life, and most applications of",
      "mechabeh",
      "are thus rabbinic prohibitions based on the ruling of the Sages, who extended the",
      "melachah",
      "to include all extinguishing, even when not done for a useful purpose.",
      "2",
      "Mechabeh With Electricity",
      "Most Rabbinic authorities say that causing a filament to glow by turning on an electric appliance is an act of",
      "mav'ir",
      "(kindling), and turning the appliance off is an act of",
      "mechabeh.",
      "3"
    ]
  },
  {
    "id": 6897566,
    "name": "Hotzaah",
    "source_url": "https://www.chabad.org/library/article_cdo/aid/6897566/jewish/Hotzaah-Transferring.htm",
    "fetch_status": "ok",
    "definition": "Carrying or transferring any item from one place to another—under certain conditions—constitutes the",
    "activities_to_avoid": null,
    "body_lines": [
      "Carrying or transferring any item from one place to another—under certain conditions—constitutes the",
      "av",
      "melachah",
      "of",
      "hotza’ah",
      "and is not permitted on",
      "Shabbat",
      ".",
      "1",
      "Its multiple layers and facets, combined with the many rabbinic prohibitions that extend from it, make the",
      "melachah",
      "of",
      "hotza’ah",
      "complex.",
      "It is particularly challenging because even scenarios that seem innocuous can fall into the category of",
      "hotza'ah",
      ". For example, if you live in an apartment building, you may not carry the garbage into the hallway to throw it down the chute without a specific type of",
      "eruv",
      "(which will be discussed below). People may be aware that an",
      "eruv",
      "is necessary to carry one’s",
      "tallit",
      "to shul or push a baby’s stroller, but connecting that to taking a few steps into the hallway of one’s own building does not seem like a natural progression.",
      "A Unique Melachah",
      "Typically, a",
      "melachah",
      "substantially changes an item.",
      "Bishul",
      ", for example, takes something that was previously raw and renders it edible.",
      "Hotza'ah"
    ]
  }
]